wagtailsweetcaptcha/__init__.py
wagtailsweetcaptcha/forms.py
wagtailsweetcaptcha/models.py
wagtailsweetcaptcha-0.1.0.dist-info/DESCRIPTION.rst
wagtailsweetcaptcha-0.1.0.dist-info/METADATA
wagtailsweetcaptcha-0.1.0.dist-info/metadata.json
wagtailsweetcaptcha-0.1.0.dist-info/RECORD
wagtailsweetcaptcha-0.1.0.dist-info/top_level.txt
wagtailsweetcaptcha-0.1.0.dist-info/WHEEL
