Metadata-Version: 2.0
Name: wagtailsweetcaptcha
Version: 0.1.0
Summary: A simple sweetcaptcha field for Wagtail Form Pages.
Home-page: http://github.com/jordij/wagtailsweetcaptcha
Author: Jordi J. Tablada
Author-email: hi@jordijoan.me
License: BSD License
Platform: UNKNOWN
Classifier: Environment :: Web Environment
Classifier: Framework :: Django
Classifier: Intended Audience :: Developers
Classifier: License :: OSI Approved :: BSD License
Classifier: Operating System :: OS Independent
Classifier: Programming Language :: Python
Classifier: Topic :: Internet :: WWW/HTTP
Classifier: Topic :: Internet :: WWW/HTTP :: Dynamic Content
Requires-Dist: django-sweetcaptcha
